py4math/__init__.py
py4math-0.0.3.dist-info/LICENSE.txt
py4math-0.0.3.dist-info/METADATA
py4math-0.0.3.dist-info/WHEEL
py4math-0.0.3.dist-info/top_level.txt
py4math-0.0.3.dist-info/RECORD
