Metadata-Version: 2.1
Name: py4math
Version: 0.0.3
Summary: A Perfect Math Module For Beginners. 
Author: Harsh Gupta
Author-email: harshnkgupta@gmail.com
Classifier: Programming Language :: Python :: 3
Classifier: License :: OSI Approved :: MIT License
Classifier: Operating System :: OS Independent
License-File: LICENSE.txt
